pgpm/__init__.py
pgpm/app.py
pgpm/settings.py
pgpm/lib/__init__.py
pgpm/lib/abstract_deploy.py
pgpm/lib/deploy.py
pgpm/lib/execute.py
pgpm/lib/install.py
pgpm/lib/version.py
pgpm/lib/db_scripts/deploy_prepare_config.sql
pgpm/lib/db_scripts/install.tmpl.sql
pgpm/lib/db_scripts/functions/_add_migration_info.sql
pgpm/lib/db_scripts/functions/_alter_schema_owner.sql
pgpm/lib/db_scripts/functions/_find_schema.sql
pgpm/lib/db_scripts/functions/_is_table_ddl_executed.sql
pgpm/lib/db_scripts/functions/_log_table_evolution.sql
pgpm/lib/db_scripts/functions/_set_revision_package.sql
pgpm/lib/db_scripts/functions/_upsert_package_info.sql
pgpm/lib/db_scripts/functions/drop_schema_smart.sql
pgpm/lib/db_scripts/functions/set_search_path.sql
pgpm/lib/db_scripts/migrations/0.0.1-0.0.6.tmpl.sql
pgpm/lib/db_scripts/migrations/0.0.7-0.1.3.tmpl.sql
pgpm/lib/db_scripts/migrations/0.1.10-0.1.10.tmpl.sql
pgpm/lib/db_scripts/migrations/0.1.11-0.1.11.tmpl.sql
pgpm/lib/db_scripts/migrations/0.1.12-0.1.12.tmpl.sql
pgpm/lib/db_scripts/migrations/0.1.13-0.1.17.tmpl.sql
pgpm/lib/db_scripts/migrations/0.1.18-0.1.18.tmpl.sql
pgpm/lib/db_scripts/migrations/0.1.19-0.1.33.tmpl.sql
pgpm/lib/db_scripts/migrations/0.1.34-0.1.59.tmpl.sql
pgpm/lib/db_scripts/migrations/0.1.4-0.1.5.tmpl.sql
pgpm/lib/db_scripts/migrations/0.1.6-0.1.7.tmpl.sql
pgpm/lib/db_scripts/migrations/0.1.8-0.1.9.tmpl.sql
pgpm/lib/db_scripts/triggers/_log_ddl_change.sql
pgpm/lib/utils/__init__.py
pgpm/lib/utils/config.py
pgpm/lib/utils/db.py
pgpm/lib/utils/misc.py
pgpm/lib/utils/vcs.py
pgpm/utils/__init__.py
pgpm/utils/config.py
pgpm/utils/issue_trackers.py
pgpm-0.1.62.dist-info/DESCRIPTION.rst
pgpm-0.1.62.dist-info/METADATA
pgpm-0.1.62.dist-info/RECORD
pgpm-0.1.62.dist-info/WHEEL
pgpm-0.1.62.dist-info/entry_points.txt
pgpm-0.1.62.dist-info/metadata.json
pgpm-0.1.62.dist-info/top_level.txt
