Metadata-Version: 2.0
Name: pgpm
Version: 0.1.62
Summary: Postgres package manager
Home-page: https://github.com/affinitas/pgpm
Author: Artem Panchoyan
Author-email: artem.panchoyan@gmail.com
License: MIT
Keywords: postgres database package deploying
Platform: UNKNOWN
Classifier: Development Status :: 3 - Alpha
Classifier: Environment :: Console
Classifier: Intended Audience :: Developers
Classifier: Intended Audience :: System Administrators
Classifier: Programming Language :: Python
Classifier: License :: OSI Approved :: MIT License
Classifier: Operating System :: MacOS
Classifier: Operating System :: Microsoft :: Windows
Classifier: Operating System :: POSIX
Classifier: Topic :: Software Development :: Build Tools
Classifier: Topic :: Utilities
Classifier: Topic :: Database
Requires-Dist: colorama
Requires-Dist: docopt
Requires-Dist: dulwich
Requires-Dist: psycopg2
Requires-Dist: requests
Requires-Dist: sqlparse
